turbine_client/__init__.py
turbine_client/auth.py
turbine_client/client.py
turbine_client/config.py
turbine_client/constants.py
turbine_client/exceptions.py
turbine_client/signer.py
turbine_client/types.py
turbine_client/utils.py
turbine_client/http/__init__.py
turbine_client/http/client.py
turbine_client/order_builder/__init__.py
turbine_client/order_builder/builder.py
turbine_client/order_builder/helpers.py
turbine_client/ws/__init__.py
turbine_client/ws/client.py
turbine_py_client-0.1.0.dist-info/licenses/LICENSE
turbine_py_client-0.1.0.dist-info/METADATA
turbine_py_client-0.1.0.dist-info/WHEEL
turbine_py_client-0.1.0.dist-info/top_level.txt
turbine_py_client-0.1.0.dist-info/RECORD
