Metadata-Version: 2.4
Name: turbine-py-client
Version: 0.1.0
Summary: Python client for Turbine CLOB prediction markets API
Author-email: Turbine Markets <engineering@turbine.markets>
License: MIT
Project-URL: Homepage, https://turbine.markets
Project-URL: Documentation, https://docs.turbine.markets
Project-URL: Repository, https://github.com/turbine/turbine-py-client
Project-URL: Issues, https://github.com/turbine/turbine-py-client/issues
Keywords: turbine,prediction-markets,clob,orderbook,ethereum,trading
Classifier: Development Status :: 4 - Beta
Classifier: Intended Audience :: Developers
Classifier: License :: OSI Approved :: MIT License
Classifier: Operating System :: OS Independent
Classifier: Programming Language :: Python :: 3
Classifier: Programming Language :: Python :: 3.9
Classifier: Programming Language :: Python :: 3.10
Classifier: Programming Language :: Python :: 3.11
Classifier: Programming Language :: Python :: 3.12
Classifier: Topic :: Software Development :: Libraries :: Python Modules
Classifier: Topic :: Office/Business :: Financial :: Investment
Requires-Python: >=3.9
License-File: LICENSE
Requires-Dist: eth-account>=0.13.0
Requires-Dist: eth-utils>=4.1.1
Requires-Dist: httpx[http2]>=0.27.0
Requires-Dist: websockets>=12.0
Requires-Dist: pynacl>=1.5.0
Requires-Dist: python-dotenv>=1.0.0
Provides-Extra: dev
Requires-Dist: pytest>=7.0.0; extra == "dev"
Requires-Dist: pytest-asyncio>=0.21.0; extra == "dev"
Requires-Dist: pytest-cov>=4.0.0; extra == "dev"
Requires-Dist: mypy>=1.0.0; extra == "dev"
Requires-Dist: ruff>=0.1.0; extra == "dev"
Requires-Dist: respx>=0.20.0; extra == "dev"
Dynamic: license-file
